pytest_parallel/__init__.py
pytest_parallel_39-0.1.0.dist-info/LICENSE
pytest_parallel_39-0.1.0.dist-info/METADATA
pytest_parallel_39-0.1.0.dist-info/WHEEL
pytest_parallel_39-0.1.0.dist-info/entry_points.txt
pytest_parallel_39-0.1.0.dist-info/top_level.txt
pytest_parallel_39-0.1.0.dist-info/RECORD
