Metadata-Version: 2.1
Name: pytest-parallel-39
Version: 0.1.0
Summary: a pytest plugin for parallel and concurrent testing
Home-page: https://github.com/browsertron/pytest-parallel
Author: Browsertron
Author-email: team@browsertron.com
License: MIT
Platform: UNKNOWN
Classifier: Development Status :: 3 - Alpha
Classifier: Intended Audience :: Developers
Classifier: Topic :: Software Development :: Testing
Classifier: Topic :: Software Development :: Quality Assurance
Classifier: Topic :: Utilities
Classifier: License :: OSI Approved :: MIT License
Classifier: Framework :: Pytest
Classifier: Operating System :: POSIX
Classifier: Operating System :: Microsoft :: Windows
Classifier: Operating System :: MacOS :: MacOS X
Classifier: Programming Language :: Python :: 3
Classifier: Programming Language :: Python :: 3.6
License-File: LICENSE
Requires-Dist: pytest (>=3.0.0)
Requires-Dist: tblib
